synstore/__init__.py
synstore-0.1.3.dist-info/LICENSE
synstore-0.1.3.dist-info/METADATA
synstore-0.1.3.dist-info/WHEEL
synstore-0.1.3.dist-info/RECORD
