Metadata-Version: 2.3
Name: synstore
Version: 0.1.3
Summary: Consistent storage for net-synergy projects.
License: MIT
Author: David Connell
Author-email: david32@dcon.addy.io
Requires-Python: >=3.10,<4.0
Classifier: License :: OSI Approved :: MIT License
Classifier: Programming Language :: Python :: 3
Classifier: Programming Language :: Python :: 3.10
Classifier: Programming Language :: Python :: 3.11
Classifier: Programming Language :: Python :: 3.12
Classifier: Programming Language :: Python :: 3.13
Requires-Dist: platformdirs (>=4.3.6,<5.0.0)
Project-URL: Repository, https://github.com/net-synergy/synstore
